parcel_details_export/__init__.py
parcel_details_export/parcel_details.py
parcel_details_export-0.2.0.dist-info/licenses/LICENSE
parcel_details_export-0.2.0.dist-info/METADATA
parcel_details_export-0.2.0.dist-info/WHEEL
parcel_details_export-0.2.0.dist-info/top_level.txt
parcel_details_export-0.2.0.dist-info/RECORD
