Metadata-Version: 2.4
Name: parcel_details_export
Version: 0.2.0
Summary: A Python library for creating PDF of parcel details
Author-email: Supreeth <x24108863@student.ncirl.ie>
License: MIT
Keywords: parcel,details
Classifier: Development Status :: 3 - Alpha
Classifier: Intended Audience :: Education
Classifier: License :: OSI Approved :: MIT License
Classifier: Operating System :: Microsoft :: Windows :: Windows 10
Classifier: Programming Language :: Python :: 3.9
Classifier: Programming Language :: Python :: 3.10
Classifier: Programming Language :: Python :: 3.11
Requires-Python: >=3.6
License-File: LICENSE
Requires-Dist: django>=4.0.0
Requires-Dist: Pillow>=10.0.0
Requires-Dist: reportlab>=4.4.5
Dynamic: license-file
